TibcoRestApi/ProcessManagerService.py
TibcoRestApi/WorkItemManagementService.py
TibcoRestApi/WorkListService.py
TibcoRestApi/__init__.py
loki_pkg-0.0.1.dev1.dist-info/METADATA
loki_pkg-0.0.1.dev1.dist-info/WHEEL
loki_pkg-0.0.1.dev1.dist-info/top_level.txt
loki_pkg-0.0.1.dev1.dist-info/RECORD
